MANIFEST.in
README.md
requirements.txt
setup.py
reveal_graph_embedding/__init__.py
reveal_graph_embedding/common.py
reveal_graph_embedding.egg-info/PKG-INFO
reveal_graph_embedding.egg-info/SOURCES.txt
reveal_graph_embedding.egg-info/dependency_links.txt
reveal_graph_embedding.egg-info/entry_points.txt
reveal_graph_embedding.egg-info/top_level.txt
reveal_graph_embedding/datautil/__init__.py
reveal_graph_embedding/datautil/datarw.py
reveal_graph_embedding/datautil/feature_rw_util.py
reveal_graph_embedding/datautil/make_directory_tree.py
reveal_graph_embedding/datautil/prediction_rw_util.py
reveal_graph_embedding/datautil/read_exotic_features.py
reveal_graph_embedding/datautil/score_rw_util.py
reveal_graph_embedding/datautil/asu_datautil/__init__.py
reveal_graph_embedding/datautil/asu_datautil/asu_read_data.py
reveal_graph_embedding/datautil/insight_datautil/__init__.py
reveal_graph_embedding/datautil/insight_datautil/insight_read_data.py
reveal_graph_embedding/datautil/snow_datautil/__init__.py
reveal_graph_embedding/datautil/snow_datautil/snow_read_data.py
reveal_graph_embedding/embedding/__init__.py
reveal_graph_embedding/embedding/common.py
reveal_graph_embedding/embedding/community_weighting.py
reveal_graph_embedding/embedding/competing_methods.py
reveal_graph_embedding/embedding/implicit.py
reveal_graph_embedding/embedding/laplacian.py
reveal_graph_embedding/embedding/arcte/__init__.py
reveal_graph_embedding/embedding/arcte/arcte.py
reveal_graph_embedding/embedding/arcte/cython_opt/__init__.py
reveal_graph_embedding/embedding/arcte/cython_opt/arcte.pyx
reveal_graph_embedding/eps_randomwalk/__init__.py
reveal_graph_embedding/eps_randomwalk/push.py
reveal_graph_embedding/eps_randomwalk/similarity.py
reveal_graph_embedding/eps_randomwalk/transition.py
reveal_graph_embedding/eps_randomwalk/benchmarks/__init__.py
reveal_graph_embedding/eps_randomwalk/benchmarks/benchmark_design.py
reveal_graph_embedding/eps_randomwalk/benchmarks/kl_divergence.py
reveal_graph_embedding/eps_randomwalk/benchmarks/time_comparisons/__init__.py
reveal_graph_embedding/eps_randomwalk/benchmarks/time_comparisons/cython_opt_comparison.py
