Metadata-Version: 1.1
Name: reveal-graph-embedding
Version: 0.1.3
Summary: Implementation of community-based graph embedding for user classification.
Home-page: https://github.com/MKLab-ITI/reveal-graph-embedding
Author: Georgios Rizos
Author-email: georgerizos@iti.gr
License: Apache
Keywords: online-social-network user-centric-pagerank user-centric-community-detection graph-embedding Reveal-FP7
Platform: UNKNOWN
Classifier: Development Status :: 2 - Pre-Alpha
Classifier: Intended Audience :: Science/Research
Classifier: License :: OSI Approved :: Apache Software License
Classifier: Natural Language :: English
Classifier: Operating System :: Unix
Classifier: Programming Language :: Cython
Classifier: Programming Language :: Python
Classifier: Programming Language :: Python :: 3
Classifier: Programming Language :: Python :: 3.4
Classifier: Programming Language :: Python :: 3 :: Only
Classifier: Programming Language :: Python :: Implementation
Classifier: Programming Language :: Python :: Implementation :: CPython
Classifier: Topic :: Scientific/Engineering :: Information Analysis
